setup.py
simple_cluster/__init__.py
simple_cluster/base_cluster.py
simple_cluster/k_means.py
simple_cluster/k_means_plus.py
simple_cluster.egg-info/PKG-INFO
simple_cluster.egg-info/SOURCES.txt
simple_cluster.egg-info/dependency_links.txt
simple_cluster.egg-info/not-zip-safe
simple_cluster.egg-info/top_level.txt